transganformer/__init__.py
transganformer/cli.py
transganformer/diff_augment.py
transganformer/transganformer.py
transganformer/version.py
transganformer-0.0.17.dist-info/LICENSE
transganformer-0.0.17.dist-info/METADATA
transganformer-0.0.17.dist-info/WHEEL
transganformer-0.0.17.dist-info/entry_points.txt
transganformer-0.0.17.dist-info/top_level.txt
transganformer-0.0.17.dist-info/RECORD
