Metadata-Version: 2.1
Name: transganformer
Version: 0.0.17
Summary: TransGanFormer
Home-page: https://github.com/lucidrains/transganformer
Author: Phil Wang
Author-email: lucidrains@gmail.com
License: MIT
Keywords: artificial intelligence,deep learning,generative adversarial networks,transformers,attention-mechanism
Platform: UNKNOWN
Classifier: Development Status :: 4 - Beta
Classifier: Intended Audience :: Developers
Classifier: Topic :: Scientific/Engineering :: Artificial Intelligence
Classifier: License :: OSI Approved :: MIT License
Classifier: Programming Language :: Python :: 3.6
Requires-Dist: einops (>=0.3)
Requires-Dist: fire
Requires-Dist: kornia
Requires-Dist: numpy
Requires-Dist: pillow
Requires-Dist: retry
Requires-Dist: torch (>=1.6)
Requires-Dist: torchvision
Requires-Dist: tqdm
